setup.cfg
setup.py
filesafe/__init__.py
filesafe.egg-info/PKG-INFO
filesafe.egg-info/SOURCES.txt
filesafe.egg-info/dependency_links.txt
filesafe.egg-info/entry_points.txt
filesafe.egg-info/top_level.txt
filesafe.egg-info/zip-safe